LICENSE
MANIFEST.in
README.rst
setup.cfg
setup.py
django_aws_zip/__init__.py
django_aws_zip/aws.py
django_aws_zip/models.py
django_aws_zip.egg-info/PKG-INFO
django_aws_zip.egg-info/SOURCES.txt
django_aws_zip.egg-info/dependency_links.txt
django_aws_zip.egg-info/requires.txt
django_aws_zip.egg-info/top_level.txt
django_aws_zip/migrations/0001_initial.py
django_aws_zip/migrations/0002_auto_20180521_0959.py
django_aws_zip/migrations/__init__.py