Metadata-Version: 1.0
Name: django-aws-zip
Version: 1.1
Summary: A simple Django app to unzip on AWS S3.
Home-page: https://github.com/paulohesilva/django_aws_zip.git
Author: Paulo Henrique da Silva
Author-email: phs.paulohenriquesilva@gmail.com
License: UNKNOWN
Keywords: aws,s3,zip
Platform: UNKNOWN
